pyproject.toml
setup.py
rqattribution_campisi/__init__.py
rqattribution_campisi/allocation_selection.py
rqattribution_campisi/analyzer.py
rqattribution_campisi/attribution.py
rqattribution_campisi/const.py
rqattribution_campisi.egg-info/PKG-INFO
rqattribution_campisi.egg-info/SOURCES.txt
rqattribution_campisi.egg-info/dependency_links.txt
rqattribution_campisi.egg-info/not-zip-safe
rqattribution_campisi.egg-info/top_level.txt