Metadata-Version: 1.2
Name: rqattribution-campisi
Version: 0.0.8
Summary: campisi model performance attribution
Home-page: https://www.ricequant.com/
Author: Ricequant
Author-email: public@ricequant.com
License: UNKNOWN
Keywords: rqattribution
Platform: UNKNOWN
Classifier: Programming Language :: Python :: 3
Classifier: Programming Language :: Python :: 3.6
Classifier: Programming Language :: Python :: 3.7
Classifier: Programming Language :: Python :: 3.8
Classifier: Intended Audience :: Developers
Classifier: Operating System :: OS Independent
Classifier: Environment :: Console
Requires-Python: >=3.6
